fastapi_base/app.py
fastapi_base/crud_app.py
fastapi_base/main.py
fastapi_base/project.py
fastapi_base/schema_generator.py
fastapi_base/utils.py
fastapi_base/samples/app/config.py
fastapi_base/samples/app/dependencies.py
fastapi_base/samples/app/models.py
fastapi_base/samples/app/schemas.py
fastapi_base/samples/app/service.py
fastapi_base/samples/app/utils.py
fastapi_base/samples/app/views.py
fastapi_base/samples/project/core/abstract_repository.py
fastapi_base/samples/project/core/database.py
fastapi_base/samples/project/core/exceptions.py
fastapi_base/samples/project/core/main.py
fastapi_base/samples/project/core/models_imports.py
fastapi_base/samples/project/core/settings.py
fastapi_base-2.12.dist-info/METADATA
fastapi_base-2.12.dist-info/WHEEL
fastapi_base-2.12.dist-info/entry_points.txt
fastapi_base-2.12.dist-info/top_level.txt
fastapi_base-2.12.dist-info/RECORD
