Metadata-Version: 2.1
Name: fastapi-base
Version: 2.12
Summary: FastAPI project structure generator
Home-page: https://github.com/idmaksim/fastapi-base
Author: Dementev Maksim
Author-email: i@dmaksim.ru
Classifier: Programming Language :: Python :: 3
Classifier: License :: OSI Approved :: MIT License
Classifier: Operating System :: OS Independent
Requires-Python: >=3.6
